progenitor_probability/__init__.py
progenitor_probability/__version__.py
progenitor_probability/fractions.dat
progenitor_probability-1.1.data/scripts/tabulate_progenitor_probability.py
progenitor_probability-1.1.dist-info/LICENSE
progenitor_probability-1.1.dist-info/METADATA
progenitor_probability-1.1.dist-info/WHEEL
progenitor_probability-1.1.dist-info/top_level.txt
progenitor_probability-1.1.dist-info/RECORD
