Metadata-Version: 2.1
Name: progenitor-probability
Version: 1.1
Summary: Returns the joint progenitor probability (probability that a galaxy is a spheroid at z=0) for a given redshift, mass, environment (percentile) and star-formation rate.
Home-page: https://github.com/garrethmartin/progenitor-fractions
Author: garrethmartin
Author-email: g.martin4@herts.ac.uk
License: MIT
Platform: UNKNOWN
Classifier: License :: OSI Approved :: MIT License
Classifier: Programming Language :: Python
Classifier: Programming Language :: Python :: 2
Classifier: Programming Language :: Python :: 2.6
Classifier: Programming Language :: Python :: 2.7
Classifier: Programming Language :: Python :: 3
Classifier: Programming Language :: Python :: 3.3
Classifier: Programming Language :: Python :: 3.4
Classifier: Programming Language :: Python :: 3.5
Classifier: Programming Language :: Python :: 3.6
Classifier: Programming Language :: Python :: 3.7
Classifier: Programming Language :: Python :: Implementation :: PyPy
Requires-Dist: numpy (>=1.14)
Requires-Dist: scipy (>=1.2)
